datin/__init__.py
datin/main.py
datin/main2.py
datin-0.1.15.dist-info/LICENSE
datin-0.1.15.dist-info/METADATA
datin-0.1.15.dist-info/WHEEL
datin-0.1.15.dist-info/top_level.txt
datin-0.1.15.dist-info/RECORD
